dfcleaner/__init__.py
dfcleaner/__main__.py
dfcleaner/cleaner.py
dfcleaner/dflogger.py
dfcleaner-1.2.0.dist-info/METADATA
dfcleaner-1.2.0.dist-info/WHEEL
dfcleaner-1.2.0.dist-info/top_level.txt
dfcleaner-1.2.0.dist-info/RECORD
