Metadata-Version: 2.1
Name: dfcleaner
Version: 1.2.0
Summary: this package contains helper methods to clean pandas dataframe quickly and therefore simplifying the data cleaning process
Home-page: https://github.com/zahash/dfcleaner
Author: zahash
Author-email: zahash.z@gmail.com
License: MIT
Platform: UNKNOWN
Classifier: License :: OSI Approved :: MIT License
Classifier: Programming Language :: Python :: 3
Classifier: Programming Language :: Python :: 3.7
Requires-Dist: pandas
Requires-Dist: numpy
